vagrant/__init__.py
vagrant/compat.py
vagrant/test.py
vagrantpy-0.6.0.dist-info/METADATA
vagrantpy-0.6.0.dist-info/RECORD
vagrantpy-0.6.0.dist-info/WHEEL
vagrantpy-0.6.0.dist-info/top_level.txt
